MemoryFrames/AppState.py
MemoryFrames/PluginInfra/Note.py
MemoryFrames/PluginInfra/NoteSource.py
MemoryFrames/PluginInfra/Plugin.py
MemoryFrames/PluginInfra/README.md
MemoryFrames/PluginInfra/Settings.py
MemoryFrames/PluginInfra/TextualUserExperienceInfo.py
MemoryFrames/PluginInfra/UserExperienceInfo.py
MemoryFrames/PluginInfra/__init__.py
MemoryFrames/TextualUserExperience.py
MemoryFrames/TextualUserExperience.tcss
MemoryFrames/__init__.py
MemoryFrames/__main__.py
MemoryFrames/py.typed
memoryframes-0.6.0.dist-info/WHEEL
memoryframes-0.6.0.dist-info/entry_points.txt
memoryframes-0.6.0.dist-info/METADATA
memoryframes-0.6.0.dist-info/RECORD
