Metadata-Version: 2.3
Name: memoryframes
Version: 0.6.0
Summary: Add your description here
Author: David Brownell
Author-email: David Brownell <github@DavidBrownell.com>
License: MIT
Classifier: Operating System :: MacOS
Classifier: Operating System :: Microsoft :: Windows
Classifier: Operating System :: POSIX :: Linux
Classifier: Programming Language :: Python
Classifier: Programming Language :: Python :: 3.14
Requires-Dist: dbrownell-common>=0.16.0
Requires-Dist: pluggy>=1.6.0
Requires-Dist: python-frontmatter>=1.1.0
Requires-Dist: rtyaml>=1.0.0
Requires-Dist: textual>=6.8.0
Requires-Dist: typer>=0.20.0
Requires-Dist: typer-config>=1.4.3
Requires-Python: >=3.14
Project-URL: Documentation, https://github.com/davidbrownell/MemoryFrames
Project-URL: Homepage, https://github.com/davidbrownell/MemoryFrames
Project-URL: Repository, https://github.com/davidbrownell/MemoryFrames
